watchm8/__init__.py
watchm8/_filter.py
watchm8/event.py
watchm8/job.py
watchm8/lib.py
watchm8/loaders.py
watchm8/actions/__init__.py
watchm8/actions/_base.py
watchm8/actions/core.py
watchm8/actions/k8s.py
watchm8/actions/say.py
watchm8/dispatchers/__init__.py
watchm8/dispatchers/_base.py
watchm8/dispatchers/core.py
watchm8/factories/__init__.py
watchm8/factories/action.py
watchm8/factories/dispatcher.py
watchm8/factories/job.py
watchm8/factories/watcher.py
watchm8/watchers/__init__.py
watchm8/watchers/_base.py
watchm8/watchers/fs.py
watchm8/watchers/k8s.py
watchm8-0.0.1a1.data/scripts/m8.py
watchm8-0.0.1a1.dist-info/DESCRIPTION.rst
watchm8-0.0.1a1.dist-info/METADATA
watchm8-0.0.1a1.dist-info/RECORD
watchm8-0.0.1a1.dist-info/WHEEL
watchm8-0.0.1a1.dist-info/metadata.json
watchm8-0.0.1a1.dist-info/top_level.txt
