Metadata-Version: 2.0
Name: watchm8
Version: 0.0.1a1
Summary: Event driven "If This Then That" like automation tool for watchable resources
Home-page: https://github.com/freach/watchm8
Author: Simon Pirschel
Author-email: simon@aboutsimon.com
License: Apache 2.0
Platform: UNKNOWN
Classifier: Development Status :: 2 - Pre-Alpha
Classifier: Intended Audience :: Developers
Classifier: Intended Audience :: System Administrators
Classifier: License :: OSI Approved :: Apache Software License
Classifier: Natural Language :: English
Classifier: Operating System :: POSIX
Classifier: Operating System :: MacOS
Classifier: Environment :: Console
Classifier: Programming Language :: Python
Classifier: Programming Language :: Python :: 2.7
Classifier: Programming Language :: Python :: 3
Classifier: Programming Language :: Python :: Implementation :: CPython
Classifier: Programming Language :: Python :: Implementation :: PyPy
Requires-Dist: Jinja2 (>=2.9.6)
Requires-Dist: kubernetes (==3.0.0)
Requires-Dist: watchdog (==0.8.3)
